{
    "https://leetcode.com/problems/2": {
        "quesName": "Problem 2",
        "quesLink": "https://leetcode.com/problems/2",
        "specialTag": "Easy",
        "tags": [
            "Array",
            "Hash Table",
            "Sorting"
        ]
    }, 
    "https://leetcode.com/problems/5": {
        "quesName": "Problem 5",
        "quesLink": "https://leetcode.com/problems/1",
        "specialTag": "Easy",
        "tags": [
            "Array",
            "Hash Table",
            "Sorting"
        ]
    }, 
    "https://leetcode.com/problems/6": {
        "quesName": "Problem 6",
        "quesLink": "https://leetcode.com/problems/6",
        "specialTag": "Easy",
        "tags": [
            "Array",
            "Hash Table",
            "Sorting"
        ]
    },
    "https://leetcode.com/problems/7": {
        "quesName": "Problem 7",
        "quesLink": "https://leetcode.com/problems/7",
        "specialTag": "Easy",
        "tags": [
            "Array",
            "Hash Table",
            "Sorting"
        ]
    },
    "https://leetcode.com/problems/9": {
        "quesName": "Problem 9",
        "quesLink": "https://leetcode.com/problems/9",
        "specialTag": "Easy",
        "tags": [
            "Array",
            "Hash Table",
            "Sorting"
        ]
    },
    "https://leetcode.com/problems/11": {
        "quesName": "Problem 11",
        "quesLink": "https://leetcode.com/problems/1",
        "specialTag": "Easy",
        "tags": [
            "Array",
            "Hash Table",
            "Sorting"
        ]
    }
}